pyprctl/__init__.py
pyprctl/caps.py
pyprctl/ffi.py
pyprctl/file_caps.py
pyprctl/fsid.py
pyprctl/misc.py
pyprctl/py.typed
pyprctl-0.1.3.dist-info/LICENSE
pyprctl-0.1.3.dist-info/METADATA
pyprctl-0.1.3.dist-info/WHEEL
pyprctl-0.1.3.dist-info/top_level.txt
pyprctl-0.1.3.dist-info/RECORD
