Metadata-Version: 2.1
Name: pyprctl
Version: 0.1.3
Summary: An interface to Linux's prctl() syscall written in pure Python using ctypes.
Home-page: https://github.com/cptpcrd/pyprctl
License: MIT
Project-URL: Documentation, https://pyprctl.readthedocs.io/en/latest
Keywords: prctl
Platform: UNKNOWN
Classifier: License :: OSI Approved :: MIT License
Classifier: Programming Language :: Python :: 3.6
Classifier: Programming Language :: Python :: 3.7
Classifier: Programming Language :: Python :: 3.8
Classifier: Programming Language :: Python :: 3.9
Classifier: Programming Language :: Python :: 3.10
Classifier: Operating System :: POSIX :: Linux
Requires-Python: >=3.6
License-File: LICENSE
Requires-Dist: dataclasses ; python_version <= "3.6"
